gpuslot/__init__.py
gpuslot/__main__.py
gpuslot/cli.py
gpuslot/core.py
gpuslot/status.py
gpuslot/tmux.py
gpuslot/utils.py
gpuslot-1.1.dist-info/LICENSE
gpuslot-1.1.dist-info/METADATA
gpuslot-1.1.dist-info/WHEEL
gpuslot-1.1.dist-info/entry_points.txt
gpuslot-1.1.dist-info/top_level.txt
gpuslot-1.1.dist-info/RECORD
