Metadata-Version: 2.1
Name: gpuslot
Version: 1.1
Summary: Job submitter for gpus
Home-page: https://github.com/yoichiro0406/gpuslot
Author: Yoichiro Hisadome
Author-email: hisadome0406@gmail.com
License: UNKNOWN
Platform: UNKNOWN
License-File: LICENSE
Requires-Dist: pynvml
Requires-Dist: rich
Requires-Dist: omegaconf
Requires-Dist: loguru
Requires-Dist: click
Requires-Dist: sh
